odoo/addons/l10n_it_delivery_note/README.rst
odoo/addons/l10n_it_delivery_note/__init__.py
odoo/addons/l10n_it_delivery_note/__manifest__.py
odoo/addons/l10n_it_delivery_note/cli/__init__.py
odoo/addons/l10n_it_delivery_note/cli/core.py
odoo/addons/l10n_it_delivery_note/cli/migrate_l10n_it_ddt.py
odoo/addons/l10n_it_delivery_note/controllers/__init__.py
odoo/addons/l10n_it_delivery_note/controllers/portal.py
odoo/addons/l10n_it_delivery_note/demo/delivery_carrier_demo.xml
odoo/addons/l10n_it_delivery_note/demo/res_partner_demo.xml
odoo/addons/l10n_it_delivery_note/i18n/fr.po
odoo/addons/l10n_it_delivery_note/i18n/it.po
odoo/addons/l10n_it_delivery_note/i18n/l10n_it_delivery_note.pot
odoo/addons/l10n_it_delivery_note/migrations/13.0.1.0.0/noupdate_changes.xml
odoo/addons/l10n_it_delivery_note/migrations/13.0.1.0.0/post-migration.py
odoo/addons/l10n_it_delivery_note/migrations/13.0.1.0.0/pre-migrate.py
odoo/addons/l10n_it_delivery_note/migrations/14.0.3.0.0/post-migrate.py
odoo/addons/l10n_it_delivery_note/mixins/__init__.py
odoo/addons/l10n_it_delivery_note/mixins/picking_checker.py
odoo/addons/l10n_it_delivery_note/mixins/shipping_updater.py
odoo/addons/l10n_it_delivery_note/models/__init__.py
odoo/addons/l10n_it_delivery_note/models/account_invoice.py
odoo/addons/l10n_it_delivery_note/models/res_company.py
odoo/addons/l10n_it_delivery_note/models/res_config_settings.py
odoo/addons/l10n_it_delivery_note/models/res_partner.py
odoo/addons/l10n_it_delivery_note/models/sale_order.py
odoo/addons/l10n_it_delivery_note/models/stock_delivery_note.py
odoo/addons/l10n_it_delivery_note/models/stock_location.py
odoo/addons/l10n_it_delivery_note/models/stock_picking.py
odoo/addons/l10n_it_delivery_note/models/stock_picking_type.py
odoo/addons/l10n_it_delivery_note/readme/CONFIGURE.rst
odoo/addons/l10n_it_delivery_note/readme/CONTRIBUTORS.rst
odoo/addons/l10n_it_delivery_note/readme/DESCRIPTION.rst
odoo/addons/l10n_it_delivery_note/readme/USAGE.rst
odoo14_addon_l10n_it_delivery_note-14.0.3.6.7.dist-info/METADATA
odoo14_addon_l10n_it_delivery_note-14.0.3.6.7.dist-info/WHEEL
odoo14_addon_l10n_it_delivery_note-14.0.3.6.7.dist-info/top_level.txt
odoo14_addon_l10n_it_delivery_note-14.0.3.6.7.dist-info/RECORD
