Metadata-Version: 2.1
Name: odoo14-addon-l10n_it_delivery_note
Version: 14.0.3.6.7
Summary: Crea, gestisce e fattura i DDT partendo dalle consegne
Home-page: https://github.com/OCA/l10n-italy
Author: Marco Calcagni, Gianmarco Conte, Link IT Europe Srl, Odoo Community Association (OCA)
Author-email: support@odoo-community.org
License: AGPL-3
Classifier: Programming Language :: Python
Classifier: Framework :: Odoo
Classifier: Framework :: Odoo :: 14.0
Classifier: License :: OSI Approved :: GNU Affero General Public License v3
Requires-Python: >=3.6
Requires-Dist: odoo14-addon-delivery-carrier-partner
Requires-Dist: odoo14-addon-l10n-it-delivery-note-base
Requires-Dist: odoo<14.1dev,>=14.0a
